<annotation>
    <folder></folder>
    <filename>frame_000781</filename>
    <path></path>
    <source>
        <database>Unknown</database>
    </source>
    <size>
        <width>1280</width>
        <height>720</height>
        <depth>3</depth>
    </size>
    <segmented>0</segmented>
    <object>
        <name>player</name>
        <pose>Unspecified</pose>
        <truncated>0</truncated>
        <difficult>0</difficult>
        <bndbox>
            <xmin>1226.4177734375</xmin>
            <ymin>330.527734375</ymin>
            <xmax>1280.0</xmax>
            <ymax>445.2457415771496</ymax>
        </bndbox>
    </object>    <object>
        <name>player</name>
        <pose>Unspecified</pose>
        <truncated>0</truncated>
        <difficult>0</difficult>
        <bndbox>
            <xmin>1211.92109375</xmin>
            <ymin>304.3283203125</ymin>
            <xmax>1251.3938125</xmax>
            <ymax>403.73909478759776</ymax>
        </bndbox>
    </object>    <object>
        <name>ref</name>
        <pose>Unspecified</pose>
        <truncated>0</truncated>
        <difficult>0</difficult>
        <bndbox>
            <xmin>1090.1595703125</xmin>
            <ymin>195.7611328125</ymin>
            <xmax>1137.1817502441415</xmax>
            <ymax>280.841281250001</ymax>
        </bndbox>
    </object>    <object>
        <name>keeper</name>
        <pose>Unspecified</pose>
        <truncated>0</truncated>
        <difficult>0</difficult>
        <bndbox>
            <xmin>1207.51109375</xmin>
            <ymin>277.6345703125</ymin>
            <xmax>1253.107656249999</xmax>
            <ymax>383.5047187500004</ymax>
        </bndbox>
    </object>    <object>
        <name>player</name>
        <pose>Unspecified</pose>
        <truncated>0</truncated>
        <difficult>0</difficult>
        <bndbox>
            <xmin>499.623046875</xmin>
            <ymin>262.1287109375</ymin>
            <xmax>551.3806250000013</xmax>
            <ymax>345.30375000000095</ymax>
        </bndbox>
    </object>    <object>
        <name>player</name>
        <pose>Unspecified</pose>
        <truncated>0</truncated>
        <difficult>0</difficult>
        <bndbox>
            <xmin>412.0330078125</xmin>
            <ymin>262.557421875</ymin>
            <xmax>465.34609423828226</xmax>
            <ymax>343.4006562500006</ymax>
        </bndbox>
    </object>    <object>
        <name>player</name>
        <pose>Unspecified</pose>
        <truncated>0</truncated>
        <difficult>0</difficult>
        <bndbox>
            <xmin>467.86796875</xmin>
            <ymin>335.1263671875</ymin>
            <xmax>527.7486297607422</xmax>
            <ymax>429.4937500000011</ymax>
        </bndbox>
    </object>    <object>
        <name>ref</name>
        <pose>Unspecified</pose>
        <truncated>0</truncated>
        <difficult>0</difficult>
        <bndbox>
            <xmin>103.4541015625</xmin>
            <ymin>235.4826171875</ymin>
            <xmax>153.30699218750087</xmax>
            <ymax>337.7566363525402</ymax>
        </bndbox>
    </object>    <object>
        <name>player</name>
        <pose>Unspecified</pose>
        <truncated>0</truncated>
        <difficult>0</difficult>
        <bndbox>
            <xmin>78.66187500000015</xmin>
            <ymin>376.8587890625</ymin>
            <xmax>159.60050933837775</xmax>
            <ymax>503.86300195312543</ymax>
        </bndbox>
    </object>    <object>
        <name>player</name>
        <pose>Unspecified</pose>
        <truncated>0</truncated>
        <difficult>0</difficult>
        <bndbox>
            <xmin>944.6103515625</xmin>
            <ymin>256.181640625</ymin>
            <xmax>1007.4369062500009</xmax>
            <ymax>336.66681250000147</ymax>
        </bndbox>
    </object>    <object>
        <name>player</name>
        <pose>Unspecified</pose>
        <truncated>0</truncated>
        <difficult>0</difficult>
        <bndbox>
            <xmin>437.13203125</xmin>
            <ymin>368.5216796875</ymin>
            <xmax>497.11443750000035</xmax>
            <ymax>477.3675937500011</ymax>
        </bndbox>
    </object>
</annotation>
