<annotation>
    <folder></folder>
    <filename>frame_002746</filename>
    <path></path>
    <source>
        <database>Unknown</database>
    </source>
    <size>
        <width>1280</width>
        <height>720</height>
        <depth>3</depth>
    </size>
    <segmented>0</segmented>
    <object>
        <name>player</name>
        <pose>Unspecified</pose>
        <truncated>0</truncated>
        <difficult>0</difficult>
        <bndbox>
            <xmin>425.248291015625</xmin>
            <ymin>445.4111328125</ymin>
            <xmax>519.7516113281254</xmax>
            <ymax>553.4066406250004</ymax>
        </bndbox>
    </object>    <object>
        <name>player</name>
        <pose>Unspecified</pose>
        <truncated>0</truncated>
        <difficult>0</difficult>
        <bndbox>
            <xmin>550.230712890625</xmin>
            <ymin>586.970458984375</ymin>
            <xmax>629.6586425781252</xmax>
            <ymax>695.5598632812512</ymax>
        </bndbox>
    </object>    <object>
        <name>player</name>
        <pose>Unspecified</pose>
        <truncated>0</truncated>
        <difficult>0</difficult>
        <bndbox>
            <xmin>815.814453125</xmin>
            <ymin>332.162353515625</ymin>
            <xmax>865.0679687500015</xmax>
            <ymax>439.2289550781261</ymax>
        </bndbox>
    </object>    <object>
        <name>player</name>
        <pose>Unspecified</pose>
        <truncated>0</truncated>
        <difficult>0</difficult>
        <bndbox>
            <xmin>1168.6572265625</xmin>
            <ymin>450.873291015625</ymin>
            <xmax>1250.535400390625</xmax>
            <ymax>596.5750000000007</ymax>
        </bndbox>
    </object>    <object>
        <name>player</name>
        <pose>Unspecified</pose>
        <truncated>0</truncated>
        <difficult>0</difficult>
        <bndbox>
            <xmin>223.60000000000036</xmin>
            <ymin>394.19970703125</ymin>
            <xmax>288.5875473022461</xmax>
            <ymax>515.5500000000006</ymax>
        </bndbox>
    </object>    <object>
        <name>player</name>
        <pose>Unspecified</pose>
        <truncated>0</truncated>
        <difficult>0</difficult>
        <bndbox>
            <xmin>993.002685546875</xmin>
            <ymin>650.522705078125</ymin>
            <xmax>1057.3250000000007</xmax>
            <ymax>720.0</ymax>
        </bndbox>
    </object>    <object>
        <name>ref</name>
        <pose>Unspecified</pose>
        <truncated>0</truncated>
        <difficult>0</difficult>
        <bndbox>
            <xmin>471.73828125</xmin>
            <ymin>598.2771484375003</ymin>
            <xmax>540.5288093566901</xmax>
            <ymax>692.7959007263185</ymax>
        </bndbox>
    </object>
</annotation>
