<annotation>
    <folder></folder>
    <filename>frame_002372</filename>
    <path></path>
    <source>
        <database>Unknown</database>
    </source>
    <size>
        <width>1280</width>
        <height>720</height>
        <depth>3</depth>
    </size>
    <segmented>0</segmented>
    <object>
        <name>player</name>
        <pose>Unspecified</pose>
        <truncated>0</truncated>
        <difficult>0</difficult>
        <bndbox>
            <xmin>596.423529411765</xmin>
            <ymin>394.90481387867646</ymin>
            <xmax>674.9418397791245</xmax>
            <ymax>529.1941176470602</ymax>
        </bndbox>
    </object>    <object>
        <name>player</name>
        <pose>Unspecified</pose>
        <truncated>0</truncated>
        <difficult>0</difficult>
        <bndbox>
            <xmin>628.2510914522059</xmin>
            <ymin>391.98586856617646</ymin>
            <xmax>708.1764705882355</xmax>
            <ymax>522.8588235294127</ymax>
        </bndbox>
    </object>    <object>
        <name>player</name>
        <pose>Unspecified</pose>
        <truncated>0</truncated>
        <difficult>0</difficult>
        <bndbox>
            <xmin>286.29595588235316</xmin>
            <ymin>302.34547334558823</ymin>
            <xmax>358.4850411359007</xmax>
            <ymax>434.11176470588316</ymax>
        </bndbox>
    </object>    <object>
        <name>player</name>
        <pose>Unspecified</pose>
        <truncated>0</truncated>
        <difficult>0</difficult>
        <bndbox>
            <xmin>536.1829963235299</xmin>
            <ymin>353.5933478860294</ymin>
            <xmax>608.9041945513561</xmax>
            <ymax>476.7579618566182</ymax>
        </bndbox>
    </object>    <object>
        <name>ref</name>
        <pose>Unspecified</pose>
        <truncated>0</truncated>
        <difficult>0</difficult>
        <bndbox>
            <xmin>536.5383157169117</xmin>
            <ymin>203.62890625</ymin>
            <xmax>589.6854204963241</xmax>
            <ymax>313.67173713235354</ymax>
        </bndbox>
    </object>    <object>
        <name>keeper</name>
        <pose>Unspecified</pose>
        <truncated>0</truncated>
        <difficult>0</difficult>
        <bndbox>
            <xmin>812.2250114889706</xmin>
            <ymin>289.10133272058823</ymin>
            <xmax>901.3170036764717</xmax>
            <ymax>386.6161764705893</ymax>
        </bndbox>
    </object>
</annotation>
