<annotation>
    <folder></folder>
    <filename>frame_002947</filename>
    <path></path>
    <source>
        <database>Unknown</database>
    </source>
    <size>
        <width>1280</width>
        <height>720</height>
        <depth>3</depth>
    </size>
    <segmented>0</segmented>
    <object>
        <name>player</name>
        <pose>Unspecified</pose>
        <truncated>0</truncated>
        <difficult>0</difficult>
        <bndbox>
            <xmin>353.38326322115387</xmin>
            <ymin>233.30476262019232</ymin>
            <xmax>400.41763822115496</xmax>
            <ymax>341.4541766826923</ymax>
        </bndbox>
    </object>    <object>
        <name>player</name>
        <pose>Unspecified</pose>
        <truncated>0</truncated>
        <difficult>0</difficult>
        <bndbox>
            <xmin>111.79230769230848</xmin>
            <ymin>530.0303485576923</ymin>
            <xmax>209.16260293813852</xmax>
            <ymax>686.4076923076932</ymax>
        </bndbox>
    </object>    <object>
        <name>player</name>
        <pose>Unspecified</pose>
        <truncated>0</truncated>
        <difficult>0</difficult>
        <bndbox>
            <xmin>582.1927584134615</xmin>
            <ymin>210.24676983173077</ymin>
            <xmax>657.1461538461543</xmax>
            <ymax>303.0076923076925</ymax>
        </bndbox>
    </object>    <object>
        <name>player</name>
        <pose>Unspecified</pose>
        <truncated>0</truncated>
        <difficult>0</difficult>
        <bndbox>
            <xmin>851.3142127403848</xmin>
            <ymin>232.5380859375</ymin>
            <xmax>908.8417806185215</xmax>
            <ymax>329.1461538461544</ymax>
        </bndbox>
    </object>    <object>
        <name>player</name>
        <pose>Unspecified</pose>
        <truncated>0</truncated>
        <difficult>0</difficult>
        <bndbox>
            <xmin>563.7411358173077</xmin>
            <ymin>204.93329326923077</ymin>
            <xmax>607.2286962655878</xmax>
            <ymax>301.3153846153852</ymax>
        </bndbox>
    </object>    <object>
        <name>ref</name>
        <pose>Unspecified</pose>
        <truncated>0</truncated>
        <difficult>0</difficult>
        <bndbox>
            <xmin>707.938266225962</xmin>
            <ymin>159.7216796875</ymin>
            <xmax>765.9000007042525</xmax>
            <ymax>252.86923076923156</ymax>
        </bndbox>
    </object>    <object>
        <name>player</name>
        <pose>Unspecified</pose>
        <truncated>0</truncated>
        <difficult>0</difficult>
        <bndbox>
            <xmin>1166.737650240385</xmin>
            <ymin>374.4885817307692</ymin>
            <xmax>1238.479255089393</xmax>
            <ymax>509.2923076923086</ymax>
        </bndbox>
    </object>    <object>
        <name>player</name>
        <pose>Unspecified</pose>
        <truncated>0</truncated>
        <difficult>0</difficult>
        <bndbox>
            <xmin>893.1651893028846</xmin>
            <ymin>200.54334435096155</ymin>
            <xmax>939.3259314903861</xmax>
            <ymax>296.911117788463</ymax>
        </bndbox>
    </object>    <object>
        <name>player</name>
        <pose>Unspecified</pose>
        <truncated>0</truncated>
        <difficult>0</difficult>
        <bndbox>
            <xmin>0.0</xmin>
            <ymin>416.689453125</ymin>
            <xmax>63.162789916993006</xmax>
            <ymax>547.4351806640625</ymax>
        </bndbox>
    </object>
</annotation>
