<annotation>
    <folder></folder>
    <filename>frame_002973</filename>
    <path></path>
    <source>
        <database>Unknown</database>
    </source>
    <size>
        <width>1280</width>
        <height>720</height>
        <depth>3</depth>
    </size>
    <segmented>0</segmented>
    <object>
        <name>player</name>
        <pose>Unspecified</pose>
        <truncated>0</truncated>
        <difficult>0</difficult>
        <bndbox>
            <xmin>477.0546875</xmin>
            <ymin>251.625390625</ymin>
            <xmax>533.4831250000013</xmax>
            <ymax>358.95011718750027</ymax>
        </bndbox>
    </object>    <object>
        <name>player</name>
        <pose>Unspecified</pose>
        <truncated>0</truncated>
        <difficult>0</difficult>
        <bndbox>
            <xmin>243.112890625</xmin>
            <ymin>483.3703125</ymin>
            <xmax>349.080000000001</xmax>
            <ymax>624.0200000000011</ymax>
        </bndbox>
    </object>    <object>
        <name>player</name>
        <pose>Unspecified</pose>
        <truncated>0</truncated>
        <difficult>0</difficult>
        <bndbox>
            <xmin>575.2392578125</xmin>
            <ymin>190.8056640625</ymin>
            <xmax>629.4200000000008</xmax>
            <ymax>292.82000000000045</ymax>
        </bndbox>
    </object>    <object>
        <name>player</name>
        <pose>Unspecified</pose>
        <truncated>0</truncated>
        <difficult>0</difficult>
        <bndbox>
            <xmin>895.99765625</xmin>
            <ymin>196.85</ymin>
            <xmax>964.8800000000003</xmax>
            <ymax>295.2800000000003</ymax>
        </bndbox>
    </object>    <object>
        <name>player</name>
        <pose>Unspecified</pose>
        <truncated>0</truncated>
        <difficult>0</difficult>
        <bndbox>
            <xmin>539.365625</xmin>
            <ymin>207.98203125</ymin>
            <xmax>596.0098829650888</xmax>
            <ymax>293.2374218750003</ymax>
        </bndbox>
    </object>    <object>
        <name>ref</name>
        <pose>Unspecified</pose>
        <truncated>0</truncated>
        <difficult>0</difficult>
        <bndbox>
            <xmin>717.4298903245195</xmin>
            <ymin>159.7216796875</ymin>
            <xmax>769.0298918503973</xmax>
            <ymax>254.0</ymax>
        </bndbox>
    </object>    <object>
        <name>player</name>
        <pose>Unspecified</pose>
        <truncated>0</truncated>
        <difficult>0</difficult>
        <bndbox>
            <xmin>903.9458984375</xmin>
            <ymin>180.398046875</ymin>
            <xmax>950.1066406250014</xmax>
            <ymax>276.76582031250143</ymax>
        </bndbox>
    </object>    <object>
        <name>player</name>
        <pose>Unspecified</pose>
        <truncated>0</truncated>
        <difficult>0</difficult>
        <bndbox>
            <xmin>235.395703125</xmin>
            <ymin>387.3451171875</ymin>
            <xmax>313.36992187500107</xmax>
            <ymax>512.2987890625009</ymax>
        </bndbox>
    </object>
</annotation>
