<annotation>
    <folder></folder>
    <filename>frame_002513</filename>
    <path></path>
    <source>
        <database>Unknown</database>
    </source>
    <size>
        <width>1280</width>
        <height>720</height>
        <depth>3</depth>
    </size>
    <segmented>0</segmented>
    <object>
        <name>player</name>
        <pose>Unspecified</pose>
        <truncated>0</truncated>
        <difficult>0</difficult>
        <bndbox>
            <xmin>1217.0667317708333</xmin>
            <ymin>442.8251953125</ymin>
            <xmax>1280.0</xmax>
            <ymax>540.4445312500011</ymax>
        </bndbox>
    </object>    <object>
        <name>player</name>
        <pose>Unspecified</pose>
        <truncated>0</truncated>
        <difficult>0</difficult>
        <bndbox>
            <xmin>1102.4514973958335</xmin>
            <ymin>173.52897135416669</ymin>
            <xmax>1157.0333333333342</xmax>
            <ymax>261.6666666666673</ymax>
        </bndbox>
    </object>    <object>
        <name>player</name>
        <pose>Unspecified</pose>
        <truncated>0</truncated>
        <difficult>0</difficult>
        <bndbox>
            <xmin>1123.8489583333333</xmin>
            <ymin>292.5179036458333</ymin>
            <xmax>1195.730598958334</xmax>
            <ymax>388.9419270833344</ymax>
        </bndbox>
    </object>    <object>
        <name>player</name>
        <pose>Unspecified</pose>
        <truncated>0</truncated>
        <difficult>0</difficult>
        <bndbox>
            <xmin>779.5791015625</xmin>
            <ymin>245.13346354166666</ymin>
            <xmax>857.6666666666666</xmax>
            <ymax>342.83333333333456</ymax>
        </bndbox>
    </object>    <object>
        <name>ref</name>
        <pose>Unspecified</pose>
        <truncated>0</truncated>
        <difficult>0</difficult>
        <bndbox>
            <xmin>906.3753255208334</xmin>
            <ymin>104.01920572916667</ymin>
            <xmax>956.1000000000004</xmax>
            <ymax>195.83333333333454</ymax>
        </bndbox>
    </object>    <object>
        <name>keeper</name>
        <pose>Unspecified</pose>
        <truncated>0</truncated>
        <difficult>0</difficult>
        <bndbox>
            <xmin>1023.7705078125</xmin>
            <ymin>178.67545572916666</ymin>
            <xmax>1096.7333333333336</xmax>
            <ymax>293.03333333333467</ymax>
        </bndbox>
    </object>    <object>
        <name>player</name>
        <pose>Unspecified</pose>
        <truncated>0</truncated>
        <difficult>0</difficult>
        <bndbox>
            <xmin>1144.8017578125</xmin>
            <ymin>342.7503255208333</ymin>
            <xmax>1227.1000000000004</xmax>
            <ymax>447.13333333333384</ymax>
        </bndbox>
    </object>    <object>
        <name>player</name>
        <pose>Unspecified</pose>
        <truncated>0</truncated>
        <difficult>0</difficult>
        <bndbox>
            <xmin>890.349609375</xmin>
            <ymin>486.302734375</ymin>
            <xmax>1002.066666666667</xmax>
            <ymax>605.8000000000011</ymax>
        </bndbox>
    </object>    <object>
        <name>player</name>
        <pose>Unspecified</pose>
        <truncated>0</truncated>
        <difficult>0</difficult>
        <bndbox>
            <xmin>414.1165364583333</xmin>
            <ymin>182.58333333333334</ymin>
            <xmax>484.4333333333343</xmax>
            <ymax>257.5666666666675</ymax>
        </bndbox>
    </object>    <object>
        <name>player</name>
        <pose>Unspecified</pose>
        <truncated>0</truncated>
        <difficult>0</difficult>
        <bndbox>
            <xmin>305.5602213541667</xmin>
            <ymin>598.2000000000002</ymin>
            <xmax>405.5000000000012</xmax>
            <ymax>720.0</ymax>
        </bndbox>
    </object>
</annotation>
